curitiba_dados_abertos/__init__.py
curitiba_dados_abertos/core/datasource.py
curitiba_dados_abertos/core/utils.py
curitiba_dados_abertos/datasources/__init__.py
curitiba_dados_abertos/datasources/ds_156.py
curitiba_dados_abertos/tests/test_DS156.py
curitiba_dados_abertos/tests/test_download_file.py
curitiba_dados_abertos-1.1.0.dist-info/LICENSE
curitiba_dados_abertos-1.1.0.dist-info/METADATA
curitiba_dados_abertos-1.1.0.dist-info/WHEEL
curitiba_dados_abertos-1.1.0.dist-info/top_level.txt
curitiba_dados_abertos-1.1.0.dist-info/RECORD
