Metadata-Version: 2.1
Name: curitiba-dados-abertos
Version: 1.1.0
Summary: API Used to ease the access to the datasets of Curitiba Dados Abertos portal
Home-page: https://github.com/CodeForCuritiba/curitiba-dados-abertos
Author: Jonhnatha Trigueiro
Author-email: joepreludian@gmail.com
License: MIT License
Platform: UNKNOWN
Requires-Dist: requests (>2.20)
